autoDBLoader/SystemLogs.py
autoDBLoader/__init__.py
autoDBLoader/cli.py
autoDBLoader/config.py
autoDBLoader/extractDB.py
autoDBLoader/insertLoader.py
autoDBLoader/validation.py
autoDBLoader/backend/main.py
autoDBLoader/frontend/configuracao.html
autoDBLoader/frontend/execucao.html
autoDBLoader/frontend/img/checkmark.png
autoDBLoader/frontend/img/copiar.png
autoDBLoader/frontend/img/excluir.png
autoDBLoader/frontend/img/pasta.png
autoDBLoader/frontend/img/seta-aparecer.png
autoDBLoader/frontend/img/seta-esconder.png
autoDBLoader/frontend/img/verificar.png
autodbloader-0.1.3.dist-info/licenses/LICENSE
autodbloader-0.1.3.dist-info/METADATA
autodbloader-0.1.3.dist-info/WHEEL
autodbloader-0.1.3.dist-info/entry_points.txt
autodbloader-0.1.3.dist-info/top_level.txt
autodbloader-0.1.3.dist-info/RECORD
