Metadata-Version: 2.4
Name: autoDBLoader
Version: 0.1.3
Summary: Ferramenta de extração e inserção de dados com interface PyPositron
Author-email: Lucas Ferreira Rodrigues <lucaslfr00@email.com>
License: MIT
Requires-Python: >=3.8
License-File: LICENSE
Requires-Dist: pandas
Requires-Dist: numpy
Requires-Dist: sqlalchemy
Requires-Dist: pywebview
Requires-Dist: py_positron
Requires-Dist: jsonschema
Requires-Dist: oracledb
Requires-Dist: pymysql
Requires-Dist: psycopg2-binary
Requires-Dist: pyarrow
Requires-Dist: psutil
Dynamic: license-file
